viznet/__init__.py
viznet/brush.py
viznet/circuit.py
viznet/cluster.py
viznet/context.py
viznet/edgenode.py
viznet/grid.py
viznet/parsecircuit.py
viznet/setting.py
viznet/setup.py
viznet/shapes.py
viznet/theme.py
viznet/utils.py
viznet/version.py
viznet/zoo.py
viznet-0.3.0.dist-info/DESCRIPTION.rst
viznet-0.3.0.dist-info/METADATA
viznet-0.3.0.dist-info/RECORD
viznet-0.3.0.dist-info/WHEEL
viznet-0.3.0.dist-info/metadata.json
viznet-0.3.0.dist-info/top_level.txt
