Metadata-Version: 2.0
Name: viznet
Version: 0.3.0
Summary: Python module for network visualization.
Home-page: https://github.com/GiggleLiu/viznet
Maintainer: Giggle Liu
Maintainer-email: cacate0129@gmail.com
License: MIT
Download-URL: https://github.com/GiggleLiu/viznet
Platform: UNKNOWN
Classifier: Development Status :: 5 - Production/Stable
Classifier: Intended Audience :: Developers
Classifier: Intended Audience :: Science/Research
Classifier: License :: OSI Approved :: MIT License
Classifier: Topic :: Scientific/Engineering
Classifier: Topic :: Software Development
Classifier: Operating System :: Microsoft :: Windows
Classifier: Operating System :: POSIX
Classifier: Operating System :: Unix
Classifier: Operating System :: MacOS
Classifier: Programming Language :: Python :: 2
Classifier: Programming Language :: Python :: 2.7
Classifier: Programming Language :: Python :: 3
Classifier: Programming Language :: Python :: 3.6
Requires-Dist: numpy
Requires-Dist: scipy
Requires-Dist: matplotlib
